squeaknode_proto/__init__.py
squeaknode_proto/lnd_pb2.py
squeaknode_proto/lnd_pb2_grpc.py
squeaknode_proto/proto.py
squeaknode_proto/squeak_admin_pb2.py
squeaknode_proto/squeak_admin_pb2_grpc.py
squeaknode_proto-0.1.7.dist-info/LICENSE
squeaknode_proto-0.1.7.dist-info/METADATA
squeaknode_proto-0.1.7.dist-info/WHEEL
squeaknode_proto-0.1.7.dist-info/top_level.txt
squeaknode_proto-0.1.7.dist-info/zip-safe
squeaknode_proto-0.1.7.dist-info/RECORD
