Metadata-Version: 2.1
Name: squeaknode-proto
Version: 0.1.7
Summary: UNKNOWN
Home-page: UNKNOWN
License: UNKNOWN
Platform: UNKNOWN
License-File: LICENSE
Requires-Dist: googleapis-common-protos (==1.53.0)
Requires-Dist: grpcio (==1.44.0)
Requires-Dist: grpcio-tools (==1.44.0)
Requires-Dist: protobuf (==3.17.0)
